ovos_skill_fallback_hivemind/LICENSE
ovos_skill_fallback_hivemind/MANIFEST.in
ovos_skill_fallback_hivemind/README.md
ovos_skill_fallback_hivemind/__init__.py
ovos_skill_fallback_hivemind/version.py
ovos_skill_fallback_hivemind/locale/en-us/asking.dialog
ovos_skill_fallback_hivemind/locale/en-us/hivemind_error.dialog
ovos_skill_fallback_hivemind/locale/fr-fr/asking.dialog
ovos_skill_fallback_hivemind/locale/fr-fr/hivemind_error.dialog
ovos_skill_fallback_hivemind/locale/nl-nl/asking.dialog
ovos_skill_fallback_hivemind/locale/nl-nl/hivemind_error.dialog
ovos_skill_fallback_hivemind/locale/pt-pt/asking.dialog
ovos_skill_fallback_hivemind/locale/pt-pt/hivemind_error.dialog
ovos_skill_fallback_hivemind/ovos_skill_fallback_hivemind.egg-info/PKG-INFO
ovos_skill_fallback_hivemind/ovos_skill_fallback_hivemind.egg-info/SOURCES.txt
ovos_skill_fallback_hivemind/ovos_skill_fallback_hivemind.egg-info/dependency_links.txt
ovos_skill_fallback_hivemind/ovos_skill_fallback_hivemind.egg-info/entry_points.txt
ovos_skill_fallback_hivemind/ovos_skill_fallback_hivemind.egg-info/requires.txt
ovos_skill_fallback_hivemind/ovos_skill_fallback_hivemind.egg-info/top_level.txt
ovos_skill_fallback_hivemind-0.0.0a10.dist-info/LICENSE
ovos_skill_fallback_hivemind-0.0.0a10.dist-info/METADATA
ovos_skill_fallback_hivemind-0.0.0a10.dist-info/WHEEL
ovos_skill_fallback_hivemind-0.0.0a10.dist-info/entry_points.txt
ovos_skill_fallback_hivemind-0.0.0a10.dist-info/top_level.txt
ovos_skill_fallback_hivemind-0.0.0a10.dist-info/RECORD
