Metadata-Version: 2.1
Name: ovos-skill-fallback-hivemind
Version: 0.0.0a10
Summary: ovos HiveMind skill
Home-page: https://github.com/JarbasHiveMind/ovos-skill-fallback-hivemind
Author: JarbasAi
Author-email: jarbasai@mailfence.com
License: Apache-2.0
Keywords: ovos skill plugin
Platform: UNKNOWN
Requires-Dist: ovos-utils >=0.0.28,~=0.0
Requires-Dist: ovos-workshop >=0.0.11,~=0.0
Requires-Dist: ovos-plugin-manager >=0.0.26a9,~=0.0
Requires-Dist: ovos-translate-server-plugin
Requires-Dist: hivemind-bus-client >=0.0.4a22
